<pkg-contents spec="1.12"><f n="LRResty.framework" o="root" g="wheel" p="16877" pt="/Library/Frameworks/LRResty.framework" m="false" t="file"><f n="Headers" o="jblues" g="wheel" p="41453"><f n="LRResty.h" o="root" g="wheel" p="33188"/><f n="LRRestyClient+DELETE.h" o="root" g="wheel" p="33188"/><f n="LRRestyClient+GET.h" o="root" g="wheel" p="33188"/><f n="LRRestyClient+POST.h" o="root" g="wheel" p="33188"/><f n="LRRestyClient+PUT.h" o="root" g="wheel" p="33188"/><f n="LRRestyClient.h" o="root" g="wheel" p="33188"/><f n="LRRestyClientBlockDelegate.h" o="root" g="wheel" p="33188"/><f n="LRRestyClientDelegate.h" o="root" g="wheel" p="33188"/><f n="LRRestyClientProxyDelegate.h" o="root" g="wheel" p="33188"/><f n="LRRestyClientResponseDelegate.h" o="root" g="wheel" p="33188"/><f n="LRRestyClientStreamingDelegate.h" o="root" g="wheel" p="33188"/><f n="LRRestyHTTPClient.h" o="root" g="wheel" p="33188"/><f n="LRRestyRequest.h" o="root" g="wheel" p="33188"/><f n="LRRestyRequestDelegate.h" o="root" g="wheel" p="33188"/><f n="LRRestyRequestPayload.h" o="root" g="wheel" p="33188"/><f n="LRRestyResource.h" o="root" g="wheel" p="33188"/><f n="LRRestyResourceDelegate.h" o="root" g="wheel" p="33188"/><f n="LRRestyResponse.h" o="root" g="wheel" p="33188"/><f n="LRRestyTypes.h" o="root" g="wheel" p="33188"/><f n="LRSynchronousProxy.h" o="root" g="wheel" p="33188"/><f n="LRURLRequestOperation.h" o="root" g="wheel" p="33188"/><f n="NSData+Base64.h" o="root" g="wheel" p="33188"/><f n="NSDictionary+QueryString.h" o="root" g="wheel" p="33188"/><f n="NSObject+Tap.h" o="root" g="wheel" p="33188"/><f n="NSRunLoop+Additions.h" o="root" g="wheel" p="33188"/><f n="NSString+QueryString.h" o="root" g="wheel" p="33188"/><f n="NSURL+QueryInspector.h" o="root" g="wheel" p="33188"/></f><f n="LRResty" o="jblues" g="wheel" p="41453"/><f n="Resources" o="jblues" g="wheel" p="41453"><f n="en.lproj" o="root" g="wheel" p="16877"><f n="InfoPlist.strings" o="root" g="wheel" p="33188"/></f><f n="Info.plist" o="root" g="wheel" p="33188"/></f><f n="Versions" o="root" g="wheel" p="16877"><f n="A" o="root" g="wheel" p="16877"><f n="Headers" o="root" g="wheel" p="16877"><f n="LRResty.h" o="root" g="wheel" p="33188"/><f n="LRRestyClient+DELETE.h" o="root" g="wheel" p="33188"/><f n="LRRestyClient+GET.h" o="root" g="wheel" p="33188"/><f n="LRRestyClient+POST.h" o="root" g="wheel" p="33188"/><f n="LRRestyClient+PUT.h" o="root" g="wheel" p="33188"/><f n="LRRestyClient.h" o="root" g="wheel" p="33188"/><f n="LRRestyClientBlockDelegate.h" o="root" g="wheel" p="33188"/><f n="LRRestyClientDelegate.h" o="root" g="wheel" p="33188"/><f n="LRRestyClientProxyDelegate.h" o="root" g="wheel" p="33188"/><f n="LRRestyClientResponseDelegate.h" o="root" g="wheel" p="33188"/><f n="LRRestyClientStreamingDelegate.h" o="root" g="wheel" p="33188"/><f n="LRRestyHTTPClient.h" o="root" g="wheel" p="33188"/><f n="LRRestyRequest.h" o="root" g="wheel" p="33188"/><f n="LRRestyRequestDelegate.h" o="root" g="wheel" p="33188"/><f n="LRRestyRequestPayload.h" o="root" g="wheel" p="33188"/><f n="LRRestyResource.h" o="root" g="wheel" p="33188"/><f n="LRRestyResourceDelegate.h" o="root" g="wheel" p="33188"/><f n="LRRestyResponse.h" o="root" g="wheel" p="33188"/><f n="LRRestyTypes.h" o="root" g="wheel" p="33188"/><f n="LRSynchronousProxy.h" o="root" g="wheel" p="33188"/><f n="LRURLRequestOperation.h" o="root" g="wheel" p="33188"/><f n="NSData+Base64.h" o="root" g="wheel" p="33188"/><f n="NSDictionary+QueryString.h" o="root" g="wheel" p="33188"/><f n="NSObject+Tap.h" o="root" g="wheel" p="33188"/><f n="NSRunLoop+Additions.h" o="root" g="wheel" p="33188"/><f n="NSString+QueryString.h" o="root" g="wheel" p="33188"/><f n="NSURL+QueryInspector.h" o="root" g="wheel" p="33188"/></f><f n="LRResty" o="root" g="wheel" p="33261"/><f n="Resources" o="root" g="wheel" p="16877"><f n="en.lproj" o="root" g="wheel" p="16877"><f n="InfoPlist.strings" o="root" g="wheel" p="33188"/></f><f n="Info.plist" o="root" g="wheel" p="33188"/></f></f><f n="Current" o="jblues" g="wheel" p="41453"><f n="Headers" o="root" g="wheel" p="16877"><f n="LRResty.h" o="root" g="wheel" p="33188"/><f n="LRRestyClient+DELETE.h" o="root" g="wheel" p="33188"/><f n="LRRestyClient+GET.h" o="root" g="wheel" p="33188"/><f n="LRRestyClient+POST.h" o="root" g="wheel" p="33188"/><f n="LRRestyClient+PUT.h" o="root" g="wheel" p="33188"/><f n="LRRestyClient.h" o="root" g="wheel" p="33188"/><f n="LRRestyClientBlockDelegate.h" o="root" g="wheel" p="33188"/><f n="LRRestyClientDelegate.h" o="root" g="wheel" p="33188"/><f n="LRRestyClientProxyDelegate.h" o="root" g="wheel" p="33188"/><f n="LRRestyClientResponseDelegate.h" o="root" g="wheel" p="33188"/><f n="LRRestyClientStreamingDelegate.h" o="root" g="wheel" p="33188"/><f n="LRRestyHTTPClient.h" o="root" g="wheel" p="33188"/><f n="LRRestyRequest.h" o="root" g="wheel" p="33188"/><f n="LRRestyRequestDelegate.h" o="root" g="wheel" p="33188"/><f n="LRRestyRequestPayload.h" o="root" g="wheel" p="33188"/><f n="LRRestyResource.h" o="root" g="wheel" p="33188"/><f n="LRRestyResourceDelegate.h" o="root" g="wheel" p="33188"/><f n="LRRestyResponse.h" o="root" g="wheel" p="33188"/><f n="LRRestyTypes.h" o="root" g="wheel" p="33188"/><f n="LRSynchronousProxy.h" o="root" g="wheel" p="33188"/><f n="LRURLRequestOperation.h" o="root" g="wheel" p="33188"/><f n="NSData+Base64.h" o="root" g="wheel" p="33188"/><f n="NSDictionary+QueryString.h" o="root" g="wheel" p="33188"/><f n="NSObject+Tap.h" o="root" g="wheel" p="33188"/><f n="NSRunLoop+Additions.h" o="root" g="wheel" p="33188"/><f n="NSString+QueryString.h" o="root" g="wheel" p="33188"/><f n="NSURL+QueryInspector.h" o="root" g="wheel" p="33188"/></f><f n="LRResty" o="root" g="wheel" p="33261"/><f n="Resources" o="root" g="wheel" p="16877"><f n="en.lproj" o="root" g="wheel" p="16877"><f n="InfoPlist.strings" o="root" g="wheel" p="33188"/></f><f n="Info.plist" o="root" g="wheel" p="33188"/></f></f></f></f></pkg-contents>